{
  "kind": "veg",
  "code": "FA2",
  "name": "樊花",
  "updated_at": "2026-04-07T07:02:01.893286+08:00",
  "latest": {
    "date": "2025-10-05",
    "price": 60.0,
    "volume": 4.0
  },
  "daily": [
    {
      "date": "2018-09-22",
      "price": 15.0,
      "volume": 16.0
    },
    {
      "date": "2018-09-23",
      "price": 17.5,
      "volume": 10.0
    },
    {
      "date": "2018-09-29",
      "price": 48.17,
      "volume": 41.0
    },
    {
      "date": "2018-09-30",
      "price": 30.0,
      "volume": 40.0
    },
    {
      "date": "2018-10-05",
      "price": 12.0,
      "volume": 17.0
    },
    {
      "date": "2018-10-06",
      "price": 12.24,
      "volume": 29.0
    },
    {
      "date": "2018-10-07",
      "price": 5.0,
      "volume": 4.0
    },
    {
      "date": "2018-10-11",
      "price": 18.87,
      "volume": 23.0
    },
    {
      "date": "2018-10-13",
      "price": 33.84,
      "volume": 21.0
    },
    {
      "date": "2018-10-16",
      "price": 70.0,
      "volume": 20.0
    },
    {
      "date": "2018-10-17",
      "price": 17.0,
      "volume": 70.0
    },
    {
      "date": "2018-10-19",
      "price": 50.0,
      "volume": 4.0
    },
    {
      "date": "2019-02-10",
      "price": 13.41,
      "volume": 41.0
    },
    {
      "date": "2019-04-23",
      "price": 68.0,
      "volume": 9.0
    },
    {
      "date": "2019-04-28",
      "price": 30.13,
      "volume": 30.0
    },
    {
      "date": "2019-04-30",
      "price": 24.29,
      "volume": 142.0
    },
    {
      "date": "2019-05-01",
      "price": 20.0,
      "volume": 14.0
    },
    {
      "date": "2019-05-02",
      "price": 10.0,
      "volume": 6.0
    },
    {
      "date": "2019-05-03",
      "price": 15.9,
      "volume": 89.0
    },
    {
      "date": "2019-05-04",
      "price": 25.0,
      "volume": 20.0
    },
    {
      "date": "2019-05-07",
      "price": 20.0,
      "volume": 32.0
    },
    {
      "date": "2019-05-08",
      "price": 15.5,
      "volume": 32.0
    },
    {
      "date": "2019-05-09",
      "price": 11.8,
      "volume": 80.0
    },
    {
      "date": "2019-05-10",
      "price": 12.5,
      "volume": 32.0
    },
    {
      "date": "2019-05-11",
      "price": 13.25,
      "volume": 32.0
    },
    {
      "date": "2019-05-12",
      "price": 10.0,
      "volume": 17.0
    },
    {
      "date": "2019-05-18",
      "price": 13.96,
      "volume": 233.0
    },
    {
      "date": "2019-05-19",
      "price": 9.34,
      "volume": 271.0
    },
    {
      "date": "2019-05-21",
      "price": 5.56,
      "volume": 697.0
    },
    {
      "date": "2019-05-22",
      "price": 6.92,
      "volume": 260.0
    },
    {
      "date": "2019-05-23",
      "price": 6.41,
      "volume": 102.0
    },
    {
      "date": "2019-05-24",
      "price": 8.46,
      "volume": 186.0
    },
    {
      "date": "2019-05-25",
      "price": 13.95,
      "volume": 59.0
    },
    {
      "date": "2019-05-29",
      "price": 9.1,
      "volume": 11.0
    },
    {
      "date": "2019-06-01",
      "price": 10.0,
      "volume": 30.0
    },
    {
      "date": "2019-06-04",
      "price": 8.1,
      "volume": 52.0
    },
    {
      "date": "2019-06-05",
      "price": 6.15,
      "volume": 120.0
    },
    {
      "date": "2019-06-06",
      "price": 5.77,
      "volume": 264.0
    },
    {
      "date": "2019-06-07",
      "price": 6.04,
      "volume": 216.0
    },
    {
      "date": "2019-06-11",
      "price": 7.02,
      "volume": 101.0
    },
    {
      "date": "2019-06-25",
      "price": 15.0,
      "volume": 8.0
    },
    {
      "date": "2019-06-26",
      "price": 8.42,
      "volume": 188.0
    },
    {
      "date": "2019-06-27",
      "price": 11.28,
      "volume": 117.0
    },
    {
      "date": "2019-06-28",
      "price": 10.0,
      "volume": 20.0
    },
    {
      "date": "2019-06-29",
      "price": 10.0,
      "volume": 20.0
    },
    {
      "date": "2019-07-05",
      "price": 10.0,
      "volume": 15.0
    },
    {
      "date": "2019-07-09",
      "price": 10.0,
      "volume": 54.0
    },
    {
      "date": "2019-07-12",
      "price": 8.9,
      "volume": 50.0
    },
    {
      "date": "2019-07-13",
      "price": 10.0,
      "volume": 32.0
    },
    {
      "date": "2019-07-14",
      "price": 2.3,
      "volume": 55.0
    },
    {
      "date": "2019-07-17",
      "price": 23.33,
      "volume": 21.0
    },
    {
      "date": "2019-07-18",
      "price": 14.26,
      "volume": 260.0
    },
    {
      "date": "2019-07-19",
      "price": 9.21,
      "volume": 235.0
    },
    {
      "date": "2019-07-20",
      "price": 8.58,
      "volume": 164.0
    },
    {
      "date": "2019-07-21",
      "price": 9.36,
      "volume": 120.0
    },
    {
      "date": "2019-07-23",
      "price": 9.0,
      "volume": 16.0
    },
    {
      "date": "2019-07-24",
      "price": 3.0,
      "volume": 6.0
    },
    {
      "date": "2019-07-31",
      "price": 10.0,
      "volume": 10.0
    },
    {
      "date": "2019-08-01",
      "price": 8.8,
      "volume": 82.0
    },
    {
      "date": "2019-08-02",
      "price": 14.7,
      "volume": 23.0
    },
    {
      "date": "2019-08-03",
      "price": 34.8,
      "volume": 81.0
    },
    {
      "date": "2019-08-04",
      "price": 10.99,
      "volume": 174.0
    },
    {
      "date": "2019-08-06",
      "price": 5.0,
      "volume": 105.0
    },
    {
      "date": "2019-08-07",
      "price": 5.0,
      "volume": 25.0
    },
    {
      "date": "2019-08-09",
      "price": 10.0,
      "volume": 40.0
    },
    {
      "date": "2019-08-11",
      "price": 7.0,
      "volume": 20.0
    },
    {
      "date": "2019-08-23",
      "price": 30.0,
      "volume": 9.0
    },
    {
      "date": "2019-08-24",
      "price": 24.25,
      "volume": 208.0
    },
    {
      "date": "2019-08-27",
      "price": 10.0,
      "volume": 40.0
    },
    {
      "date": "2019-08-28",
      "price": 13.3,
      "volume": 16.0
    },
    {
      "date": "2019-08-29",
      "price": 17.0,
      "volume": 12.0
    },
    {
      "date": "2019-09-01",
      "price": 10.0,
      "volume": 13.0
    },
    {
      "date": "2019-09-04",
      "price": 12.0,
      "volume": 7.0
    },
    {
      "date": "2019-09-07",
      "price": 12.89,
      "volume": 36.0
    },
    {
      "date": "2019-09-08",
      "price": 35.97,
      "volume": 27.0
    },
    {
      "date": "2019-09-10",
      "price": 13.48,
      "volume": 29.0
    },
    {
      "date": "2019-09-11",
      "price": 13.0,
      "volume": 19.0
    },
    {
      "date": "2019-09-17",
      "price": 12.53,
      "volume": 111.0
    },
    {
      "date": "2019-09-18",
      "price": 13.36,
      "volume": 93.0
    },
    {
      "date": "2019-09-19",
      "price": 10.0,
      "volume": 9.0
    },
    {
      "date": "2019-09-20",
      "price": 14.93,
      "volume": 129.0
    },
    {
      "date": "2019-09-21",
      "price": 10.58,
      "volume": 19.0
    },
    {
      "date": "2019-10-01",
      "price": 13.67,
      "volume": 48.0
    },
    {
      "date": "2019-10-02",
      "price": 10.94,
      "volume": 34.0
    },
    {
      "date": "2019-10-03",
      "price": 25.31,
      "volume": 51.0
    },
    {
      "date": "2019-10-04",
      "price": 16.54,
      "volume": 181.0
    },
    {
      "date": "2019-10-06",
      "price": 8.0,
      "volume": 124.0
    },
    {
      "date": "2019-10-08",
      "price": 8.51,
      "volume": 79.0
    },
    {
      "date": "2019-10-10",
      "price": 5.0,
      "volume": 20.0
    },
    {
      "date": "2019-10-12",
      "price": 3.0,
      "volume": 80.0
    },
    {
      "date": "2019-10-15",
      "price": 5.0,
      "volume": 2.0
    },
    {
      "date": "2019-12-08",
      "price": 60.0,
      "volume": 90.0
    },
    {
      "date": "2020-04-22",
      "price": 15.0,
      "volume": 14.0
    },
    {
      "date": "2020-05-07",
      "price": 25.0,
      "volume": 30.0
    },
    {
      "date": "2020-05-08",
      "price": 15.0,
      "volume": 10.0
    },
    {
      "date": "2020-05-09",
      "price": 9.2,
      "volume": 96.0
    },
    {
      "date": "2020-05-10",
      "price": 5.81,
      "volume": 321.0
    },
    {
      "date": "2020-05-12",
      "price": 8.53,
      "volume": 51.0
    },
    {
      "date": "2020-05-13",
      "price": 16.0,
      "volume": 28.0
    },
    {
      "date": "2020-05-14",
      "price": 18.0,
      "volume": 21.0
    },
    {
      "date": "2020-05-15",
      "price": 10.0,
      "volume": 17.0
    },
    {
      "date": "2020-05-16",
      "price": 5.59,
      "volume": 54.0
    },
    {
      "date": "2020-05-27",
      "price": 30.0,
      "volume": 12.0
    },
    {
      "date": "2020-05-28",
      "price": 32.96,
      "volume": 27.0
    },
    {
      "date": "2020-05-30",
      "price": 7.74,
      "volume": 61.0
    },
    {
      "date": "2020-06-02",
      "price": 15.0,
      "volume": 54.0
    },
    {
      "date": "2020-06-03",
      "price": 16.72,
      "volume": 118.0
    },
    {
      "date": "2020-06-04",
      "price": 20.0,
      "volume": 8.0
    },
    {
      "date": "2020-06-05",
      "price": 8.75,
      "volume": 104.0
    },
    {
      "date": "2020-06-06",
      "price": 7.44,
      "volume": 36.0
    },
    {
      "date": "2020-06-09",
      "price": 7.36,
      "volume": 75.0
    },
    {
      "date": "2020-06-21",
      "price": 15.31,
      "volume": 74.0
    },
    {
      "date": "2020-06-23",
      "price": 10.53,
      "volume": 299.0
    },
    {
      "date": "2020-06-24",
      "price": 5.47,
      "volume": 246.0
    },
    {
      "date": "2020-06-25",
      "price": 4.96,
      "volume": 81.0
    },
    {
      "date": "2020-07-07",
      "price": 10.0,
      "volume": 11.0
    },
    {
      "date": "2020-07-09",
      "price": 21.2,
      "volume": 45.0
    },
    {
      "date": "2020-07-10",
      "price": 10.0,
      "volume": 10.0
    },
    {
      "date": "2020-07-11",
      "price": 22.1,
      "volume": 64.0
    },
    {
      "date": "2020-07-12",
      "price": 23.0,
      "volume": 40.0
    },
    {
      "date": "2020-07-14",
      "price": 10.2,
      "volume": 176.0
    },
    {
      "date": "2020-07-15",
      "price": 5.85,
      "volume": 125.0
    },
    {
      "date": "2020-07-17",
      "price": 10.22,
      "volume": 130.0
    },
    {
      "date": "2020-07-18",
      "price": 4.28,
      "volume": 72.0
    },
    {
      "date": "2020-07-21",
      "price": 5.0,
      "volume": 40.0
    },
    {
      "date": "2020-07-29",
      "price": 12.08,
      "volume": 96.0
    },
    {
      "date": "2020-08-02",
      "price": 10.0,
      "volume": 26.0
    },
    {
      "date": "2020-08-05",
      "price": 31.0,
      "volume": 20.0
    },
    {
      "date": "2020-08-11",
      "price": 21.33,
      "volume": 48.0
    },
    {
      "date": "2020-08-12",
      "price": 15.46,
      "volume": 62.0
    },
    {
      "date": "2020-08-14",
      "price": 14.54,
      "volume": 82.0
    },
    {
      "date": "2020-08-15",
      "price": 11.0,
      "volume": 39.0
    },
    {
      "date": "2020-08-16",
      "price": 12.0,
      "volume": 18.0
    },
    {
      "date": "2020-08-18",
      "price": 15.82,
      "volume": 247.0
    },
    {
      "date": "2020-08-19",
      "price": 6.0,
      "volume": 120.0
    },
    {
      "date": "2020-08-20",
      "price": 24.9,
      "volume": 55.0
    },
    {
      "date": "2020-08-21",
      "price": 8.0,
      "volume": 15.0
    },
    {
      "date": "2020-08-25",
      "price": 25.1,
      "volume": 29.0
    },
    {
      "date": "2020-08-26",
      "price": 9.19,
      "volume": 96.0
    },
    {
      "date": "2020-08-27",
      "price": 10.0,
      "volume": 38.0
    },
    {
      "date": "2020-08-29",
      "price": 19.0,
      "volume": 16.0
    },
    {
      "date": "2020-09-02",
      "price": 2.0,
      "volume": 40.0
    },
    {
      "date": "2020-09-09",
      "price": 20.22,
      "volume": 153.0
    },
    {
      "date": "2020-09-10",
      "price": 12.57,
      "volume": 139.0
    },
    {
      "date": "2020-09-11",
      "price": 6.67,
      "volume": 115.0
    },
    {
      "date": "2020-09-12",
      "price": 7.88,
      "volume": 234.0
    },
    {
      "date": "2020-09-13",
      "price": 4.93,
      "volume": 253.0
    },
    {
      "date": "2020-09-15",
      "price": 7.0,
      "volume": 16.0
    },
    {
      "date": "2020-09-27",
      "price": 22.0,
      "volume": 6.0
    },
    {
      "date": "2020-10-06",
      "price": 25.0,
      "volume": 20.0
    },
    {
      "date": "2020-10-11",
      "price": 22.0,
      "volume": 29.0
    },
    {
      "date": "2020-10-13",
      "price": 27.67,
      "volume": 18.0
    },
    {
      "date": "2020-10-14",
      "price": 7.6,
      "volume": 99.0
    },
    {
      "date": "2021-03-03",
      "price": 90.0,
      "volume": 25.0
    },
    {
      "date": "2021-04-08",
      "price": 25.83,
      "volume": 64.0
    },
    {
      "date": "2021-04-09",
      "price": 35.0,
      "volume": 38.0
    },
    {
      "date": "2021-04-10",
      "price": 65.0,
      "volume": 19.0
    },
    {
      "date": "2021-04-11",
      "price": 31.3,
      "volume": 27.0
    },
    {
      "date": "2021-04-25",
      "price": 25.0,
      "volume": 38.0
    },
    {
      "date": "2021-05-11",
      "price": 15.0,
      "volume": 45.0
    },
    {
      "date": "2021-05-12",
      "price": 12.0,
      "volume": 121.0
    },
    {
      "date": "2021-05-13",
      "price": 10.31,
      "volume": 178.0
    },
    {
      "date": "2021-05-14",
      "price": 8.6,
      "volume": 144.0
    },
    {
      "date": "2021-05-15",
      "price": 18.53,
      "volume": 61.0
    },
    {
      "date": "2021-05-16",
      "price": 9.19,
      "volume": 48.0
    },
    {
      "date": "2021-06-10",
      "price": 15.0,
      "volume": 12.0
    },
    {
      "date": "2021-06-12",
      "price": 5.93,
      "volume": 108.0
    },
    {
      "date": "2021-06-13",
      "price": 6.29,
      "volume": 145.0
    },
    {
      "date": "2021-06-17",
      "price": 4.62,
      "volume": 102.0
    },
    {
      "date": "2021-06-18",
      "price": 3.63,
      "volume": 158.0
    },
    {
      "date": "2021-06-19",
      "price": 6.33,
      "volume": 78.0
    },
    {
      "date": "2021-06-26",
      "price": 4.8,
      "volume": 65.0
    },
    {
      "date": "2021-07-04",
      "price": 5.5,
      "volume": 30.0
    },
    {
      "date": "2021-07-06",
      "price": 5.73,
      "volume": 138.0
    },
    {
      "date": "2021-07-07",
      "price": 4.48,
      "volume": 60.0
    },
    {
      "date": "2021-07-08",
      "price": 5.0,
      "volume": 12.0
    },
    {
      "date": "2021-07-09",
      "price": 6.7,
      "volume": 80.0
    },
    {
      "date": "2021-07-27",
      "price": 6.26,
      "volume": 34.0
    },
    {
      "date": "2021-07-28",
      "price": 4.0,
      "volume": 33.0
    },
    {
      "date": "2021-07-29",
      "price": 10.0,
      "volume": 24.0
    },
    {
      "date": "2021-07-31",
      "price": 10.0,
      "volume": 20.0
    },
    {
      "date": "2021-08-14",
      "price": 120.0,
      "volume": 19.0
    },
    {
      "date": "2021-08-15",
      "price": 15.67,
      "volume": 111.0
    },
    {
      "date": "2021-08-17",
      "price": 30.0,
      "volume": 30.0
    },
    {
      "date": "2021-08-18",
      "price": 18.1,
      "volume": 48.0
    },
    {
      "date": "2021-08-21",
      "price": 15.0,
      "volume": 26.0
    },
    {
      "date": "2021-09-01",
      "price": 16.42,
      "volume": 29.0
    },
    {
      "date": "2021-09-02",
      "price": 12.3,
      "volume": 30.0
    },
    {
      "date": "2021-09-03",
      "price": 12.0,
      "volume": 14.0
    },
    {
      "date": "2021-09-04",
      "price": 14.0,
      "volume": 40.0
    },
    {
      "date": "2021-09-07",
      "price": 17.0,
      "volume": 40.0
    },
    {
      "date": "2021-09-08",
      "price": 6.0,
      "volume": 40.0
    },
    {
      "date": "2021-09-09",
      "price": 9.0,
      "volume": 53.0
    },
    {
      "date": "2021-09-24",
      "price": 15.0,
      "volume": 13.0
    },
    {
      "date": "2021-09-25",
      "price": 10.41,
      "volume": 64.0
    },
    {
      "date": "2021-09-26",
      "price": 13.27,
      "volume": 121.0
    },
    {
      "date": "2021-09-28",
      "price": 11.64,
      "volume": 58.0
    },
    {
      "date": "2021-10-12",
      "price": 180.0,
      "volume": 16.0
    },
    {
      "date": "2021-10-28",
      "price": 15.0,
      "volume": 8.0
    },
    {
      "date": "2021-10-29",
      "price": 15.0,
      "volume": 18.0
    },
    {
      "date": "2021-10-30",
      "price": 17.05,
      "volume": 44.0
    },
    {
      "date": "2021-11-02",
      "price": 13.5,
      "volume": 16.0
    },
    {
      "date": "2022-05-05",
      "price": 30.0,
      "volume": 6.0
    },
    {
      "date": "2022-05-15",
      "price": 20.0,
      "volume": 31.0
    },
    {
      "date": "2022-05-20",
      "price": 18.92,
      "volume": 79.0
    },
    {
      "date": "2022-05-24",
      "price": 10.0,
      "volume": 22.0
    },
    {
      "date": "2022-05-31",
      "price": 20.0,
      "volume": 33.0
    },
    {
      "date": "2022-06-01",
      "price": 16.0,
      "volume": 66.0
    },
    {
      "date": "2022-06-10",
      "price": 15.0,
      "volume": 3.0
    },
    {
      "date": "2022-06-21",
      "price": 15.0,
      "volume": 8.0
    },
    {
      "date": "2022-06-22",
      "price": 17.69,
      "volume": 130.0
    },
    {
      "date": "2022-06-23",
      "price": 19.22,
      "volume": 146.0
    },
    {
      "date": "2022-06-24",
      "price": 15.1,
      "volume": 101.0
    },
    {
      "date": "2022-06-25",
      "price": 11.14,
      "volume": 37.0
    },
    {
      "date": "2022-06-26",
      "price": 18.41,
      "volume": 81.0
    },
    {
      "date": "2022-07-09",
      "price": 23.11,
      "volume": 104.0
    },
    {
      "date": "2022-07-10",
      "price": 15.0,
      "volume": 76.0
    },
    {
      "date": "2022-07-12",
      "price": 5.0,
      "volume": 31.0
    },
    {
      "date": "2022-07-13",
      "price": 20.0,
      "volume": 11.0
    },
    {
      "date": "2022-07-15",
      "price": 16.6,
      "volume": 14.0
    },
    {
      "date": "2022-07-27",
      "price": 23.51,
      "volume": 47.0
    },
    {
      "date": "2022-07-28",
      "price": 13.04,
      "volume": 84.0
    },
    {
      "date": "2022-07-29",
      "price": 9.71,
      "volume": 131.0
    },
    {
      "date": "2022-07-30",
      "price": 8.99,
      "volume": 85.0
    },
    {
      "date": "2022-08-02",
      "price": 12.35,
      "volume": 40.0
    },
    {
      "date": "2022-08-03",
      "price": 12.0,
      "volume": 12.0
    },
    {
      "date": "2022-08-11",
      "price": 25.29,
      "volume": 40.0
    },
    {
      "date": "2022-08-17",
      "price": 12.01,
      "volume": 448.0
    },
    {
      "date": "2022-08-18",
      "price": 10.62,
      "volume": 201.0
    },
    {
      "date": "2022-08-19",
      "price": 10.0,
      "volume": 75.0
    },
    {
      "date": "2022-08-20",
      "price": 8.0,
      "volume": 33.0
    },
    {
      "date": "2022-08-21",
      "price": 7.58,
      "volume": 54.0
    },
    {
      "date": "2022-08-23",
      "price": 8.0,
      "volume": 10.0
    },
    {
      "date": "2022-08-28",
      "price": 40.0,
      "volume": 10.0
    },
    {
      "date": "2022-09-08",
      "price": 23.33,
      "volume": 27.0
    },
    {
      "date": "2022-09-09",
      "price": 15.0,
      "volume": 17.0
    },
    {
      "date": "2022-09-10",
      "price": 44.6,
      "volume": 75.0
    },
    {
      "date": "2022-09-11",
      "price": 25.0,
      "volume": 9.0
    },
    {
      "date": "2022-09-14",
      "price": 20.0,
      "volume": 37.0
    },
    {
      "date": "2022-09-15",
      "price": 6.0,
      "volume": 10.0
    },
    {
      "date": "2022-09-16",
      "price": 35.0,
      "volume": 15.0
    },
    {
      "date": "2022-09-17",
      "price": 30.0,
      "volume": 4.0
    },
    {
      "date": "2022-09-18",
      "price": 15.14,
      "volume": 35.0
    },
    {
      "date": "2022-09-24",
      "price": 35.0,
      "volume": 11.0
    },
    {
      "date": "2022-09-28",
      "price": 25.0,
      "volume": 5.0
    },
    {
      "date": "2022-10-02",
      "price": 41.51,
      "volume": 20.0
    },
    {
      "date": "2022-10-04",
      "price": 38.6,
      "volume": 25.0
    },
    {
      "date": "2022-10-06",
      "price": 20.69,
      "volume": 82.0
    },
    {
      "date": "2022-10-08",
      "price": 17.81,
      "volume": 40.0
    },
    {
      "date": "2022-10-09",
      "price": 10.0,
      "volume": 12.0
    },
    {
      "date": "2022-10-22",
      "price": 52.0,
      "volume": 14.0
    },
    {
      "date": "2022-10-26",
      "price": 30.0,
      "volume": 21.0
    },
    {
      "date": "2022-10-27",
      "price": 26.75,
      "volume": 20.0
    },
    {
      "date": "2022-10-28",
      "price": 37.0,
      "volume": 9.0
    },
    {
      "date": "2022-10-30",
      "price": 30.0,
      "volume": 7.0
    },
    {
      "date": "2022-11-01",
      "price": 10.0,
      "volume": 14.0
    },
    {
      "date": "2022-11-22",
      "price": 25.0,
      "volume": 10.0
    },
    {
      "date": "2022-11-27",
      "price": 10.0,
      "volume": 2.0
    },
    {
      "date": "2023-04-18",
      "price": 13.0,
      "volume": 8.0
    },
    {
      "date": "2023-04-23",
      "price": 10.0,
      "volume": 24.0
    },
    {
      "date": "2023-04-25",
      "price": 8.0,
      "volume": 28.0
    },
    {
      "date": "2023-05-03",
      "price": 20.7,
      "volume": 60.0
    },
    {
      "date": "2023-05-04",
      "price": 36.16,
      "volume": 259.0
    },
    {
      "date": "2023-05-07",
      "price": 25.6,
      "volume": 19.0
    },
    {
      "date": "2023-05-09",
      "price": 26.9,
      "volume": 50.0
    },
    {
      "date": "2023-05-23",
      "price": 16.0,
      "volume": 184.0
    },
    {
      "date": "2023-05-24",
      "price": 20.95,
      "volume": 58.0
    },
    {
      "date": "2023-05-26",
      "price": 13.31,
      "volume": 240.0
    },
    {
      "date": "2023-05-27",
      "price": 9.52,
      "volume": 138.0
    },
    {
      "date": "2023-05-28",
      "price": 5.47,
      "volume": 177.0
    },
    {
      "date": "2023-05-30",
      "price": 25.55,
      "volume": 147.0
    },
    {
      "date": "2023-06-04",
      "price": 11.7,
      "volume": 36.0
    },
    {
      "date": "2023-06-11",
      "price": 28.2,
      "volume": 97.0
    },
    {
      "date": "2023-06-16",
      "price": 10.96,
      "volume": 28.0
    },
    {
      "date": "2023-06-18",
      "price": 7.0,
      "volume": 16.0
    },
    {
      "date": "2023-06-20",
      "price": 5.0,
      "volume": 37.0
    },
    {
      "date": "2023-06-22",
      "price": 18.0,
      "volume": 54.0
    },
    {
      "date": "2023-06-25",
      "price": 7.0,
      "volume": 61.0
    },
    {
      "date": "2023-06-29",
      "price": 40.0,
      "volume": 20.0
    },
    {
      "date": "2023-07-11",
      "price": 8.0,
      "volume": 21.0
    },
    {
      "date": "2023-07-12",
      "price": 37.4,
      "volume": 23.0
    },
    {
      "date": "2023-07-14",
      "price": 9.21,
      "volume": 71.0
    },
    {
      "date": "2023-07-15",
      "price": 9.04,
      "volume": 25.0
    },
    {
      "date": "2023-07-21",
      "price": 60.0,
      "volume": 16.0
    },
    {
      "date": "2023-07-25",
      "price": 22.0,
      "volume": 18.0
    },
    {
      "date": "2023-07-30",
      "price": 15.0,
      "volume": 12.0
    },
    {
      "date": "2023-08-01",
      "price": 11.67,
      "volume": 39.0
    },
    {
      "date": "2023-08-10",
      "price": 7.0,
      "volume": 16.0
    },
    {
      "date": "2023-08-11",
      "price": 20.01,
      "volume": 41.0
    },
    {
      "date": "2023-08-12",
      "price": 28.0,
      "volume": 30.0
    },
    {
      "date": "2023-08-24",
      "price": 32.7,
      "volume": 12.0
    },
    {
      "date": "2023-08-25",
      "price": 30.0,
      "volume": 15.0
    },
    {
      "date": "2023-08-26",
      "price": 25.3,
      "volume": 45.0
    },
    {
      "date": "2023-08-27",
      "price": 30.0,
      "volume": 15.0
    },
    {
      "date": "2023-08-29",
      "price": 10.0,
      "volume": 19.0
    },
    {
      "date": "2023-08-30",
      "price": 25.0,
      "volume": 6.0
    },
    {
      "date": "2023-09-02",
      "price": 35.0,
      "volume": 5.0
    },
    {
      "date": "2023-09-06",
      "price": 33.8,
      "volume": 19.0
    },
    {
      "date": "2023-09-10",
      "price": 35.0,
      "volume": 9.0
    },
    {
      "date": "2023-09-12",
      "price": 20.0,
      "volume": 39.0
    },
    {
      "date": "2023-09-13",
      "price": 10.0,
      "volume": 45.0
    },
    {
      "date": "2023-09-14",
      "price": 60.0,
      "volume": 18.0
    },
    {
      "date": "2023-09-15",
      "price": 20.96,
      "volume": 149.0
    },
    {
      "date": "2023-09-16",
      "price": 11.87,
      "volume": 265.0
    },
    {
      "date": "2023-09-17",
      "price": 9.45,
      "volume": 306.0
    },
    {
      "date": "2023-09-19",
      "price": 8.07,
      "volume": 190.0
    },
    {
      "date": "2023-09-21",
      "price": 8.9,
      "volume": 62.0
    },
    {
      "date": "2023-10-10",
      "price": 25.0,
      "volume": 16.0
    },
    {
      "date": "2023-10-20",
      "price": 15.4,
      "volume": 28.0
    },
    {
      "date": "2023-10-21",
      "price": 12.58,
      "volume": 38.0
    },
    {
      "date": "2024-04-30",
      "price": 4.6,
      "volume": 202.0
    },
    {
      "date": "2024-05-07",
      "price": 17.9,
      "volume": 84.0
    },
    {
      "date": "2024-05-10",
      "price": 15.44,
      "volume": 153.0
    },
    {
      "date": "2024-05-11",
      "price": 10.45,
      "volume": 248.0
    },
    {
      "date": "2024-05-12",
      "price": 9.49,
      "volume": 35.0
    },
    {
      "date": "2024-05-15",
      "price": 10.0,
      "volume": 21.0
    },
    {
      "date": "2024-06-08",
      "price": 28.3,
      "volume": 51.0
    },
    {
      "date": "2024-06-18",
      "price": 9.6,
      "volume": 34.0
    },
    {
      "date": "2024-07-07",
      "price": 10.0,
      "volume": 13.0
    },
    {
      "date": "2024-08-07",
      "price": 32.1,
      "volume": 35.0
    },
    {
      "date": "2024-08-08",
      "price": 13.0,
      "volume": 67.0
    },
    {
      "date": "2024-08-10",
      "price": 12.7,
      "volume": 22.0
    },
    {
      "date": "2024-08-11",
      "price": 14.18,
      "volume": 17.0
    },
    {
      "date": "2024-08-13",
      "price": 5.0,
      "volume": 24.0
    },
    {
      "date": "2024-08-15",
      "price": 5.0,
      "volume": 22.0
    },
    {
      "date": "2024-08-16",
      "price": 8.33,
      "volume": 36.0
    },
    {
      "date": "2024-08-17",
      "price": 8.75,
      "volume": 16.0
    },
    {
      "date": "2024-08-18",
      "price": 9.15,
      "volume": 30.0
    },
    {
      "date": "2024-08-21",
      "price": 11.04,
      "volume": 170.0
    },
    {
      "date": "2024-08-24",
      "price": 50.0,
      "volume": 21.0
    },
    {
      "date": "2024-08-27",
      "price": 10.0,
      "volume": 5.0
    },
    {
      "date": "2024-08-29",
      "price": 10.0,
      "volume": 79.0
    },
    {
      "date": "2024-08-30",
      "price": 9.05,
      "volume": 88.0
    },
    {
      "date": "2024-09-01",
      "price": 9.26,
      "volume": 23.0
    },
    {
      "date": "2024-09-21",
      "price": 5.0,
      "volume": 9.0
    },
    {
      "date": "2024-09-25",
      "price": 15.0,
      "volume": 10.0
    },
    {
      "date": "2024-10-02",
      "price": 10.0,
      "volume": 18.0
    },
    {
      "date": "2024-10-03",
      "price": 15.0,
      "volume": 18.0
    },
    {
      "date": "2024-12-08",
      "price": 27.7,
      "volume": 150.0
    },
    {
      "date": "2025-05-29",
      "price": 12.0,
      "volume": 26.0
    },
    {
      "date": "2025-05-30",
      "price": 60.0,
      "volume": 19.0
    },
    {
      "date": "2025-06-25",
      "price": 60.0,
      "volume": 9.0
    },
    {
      "date": "2025-07-01",
      "price": 10.0,
      "volume": 26.0
    },
    {
      "date": "2025-07-04",
      "price": 60.0,
      "volume": 30.0
    },
    {
      "date": "2025-07-09",
      "price": 60.0,
      "volume": 19.0
    },
    {
      "date": "2025-07-18",
      "price": 60.0,
      "volume": 12.0
    },
    {
      "date": "2025-07-20",
      "price": 16.21,
      "volume": 70.0
    },
    {
      "date": "2025-07-22",
      "price": 12.68,
      "volume": 149.0
    },
    {
      "date": "2025-07-23",
      "price": 12.23,
      "volume": 61.0
    },
    {
      "date": "2025-07-24",
      "price": 13.87,
      "volume": 95.0
    },
    {
      "date": "2025-07-25",
      "price": 12.14,
      "volume": 119.0
    },
    {
      "date": "2025-08-05",
      "price": 20.43,
      "volume": 77.0
    },
    {
      "date": "2025-08-08",
      "price": 60.0,
      "volume": 40.0
    },
    {
      "date": "2025-08-09",
      "price": 15.5,
      "volume": 40.0
    },
    {
      "date": "2025-08-10",
      "price": 11.67,
      "volume": 60.0
    },
    {
      "date": "2025-08-13",
      "price": 24.5,
      "volume": 48.0
    },
    {
      "date": "2025-08-15",
      "price": 17.77,
      "volume": 161.0
    },
    {
      "date": "2025-08-17",
      "price": 5.0,
      "volume": 40.0
    },
    {
      "date": "2025-08-26",
      "price": 10.0,
      "volume": 9.0
    },
    {
      "date": "2025-08-29",
      "price": 32.0,
      "volume": 30.0
    },
    {
      "date": "2025-09-04",
      "price": 17.76,
      "volume": 38.0
    },
    {
      "date": "2025-09-05",
      "price": 20.0,
      "volume": 13.0
    },
    {
      "date": "2025-09-17",
      "price": 23.76,
      "volume": 74.0
    },
    {
      "date": "2025-09-18",
      "price": 20.23,
      "volume": 87.0
    },
    {
      "date": "2025-10-05",
      "price": 60.0,
      "volume": 4.0
    }
  ],
  "weekly": [
    {
      "key": "2006-W20",
      "price": 10.0,
      "volume": 12.0
    },
    {
      "key": "2006-W21",
      "price": 120.0,
      "volume": 10.0
    },
    {
      "key": "2006-W22",
      "price": 15.0,
      "volume": 16.0
    },
    {
      "key": "2006-W23",
      "price": 8.14,
      "volume": 78.0
    },
    {
      "key": "2006-W24",
      "price": 8.59,
      "volume": 346.0
    },
    {
      "key": "2006-W25",
      "price": 5.63,
      "volume": 426.0
    },
    {
      "key": "2006-W29",
      "price": 10.0,
      "volume": 20.0
    },
    {
      "key": "2006-W30",
      "price": 10.26,
      "volume": 408.0
    },
    {
      "key": "2006-W32",
      "price": 5.53,
      "volume": 200.0
    },
    {
      "key": "2006-W33",
      "price": 10.0,
      "volume": 19.0
    },
    {
      "key": "2006-W34",
      "price": 6.0,
      "volume": 21.0
    },
    {
      "key": "2006-W35",
      "price": 8.0,
      "volume": 6.0
    },
    {
      "key": "2006-W36",
      "price": 72.92,
      "volume": 96.0
    },
    {
      "key": "2006-W39",
      "price": 9.1,
      "volume": 61.0
    },
    {
      "key": "2007-W21",
      "price": 6.46,
      "volume": 46.0
    },
    {
      "key": "2007-W23",
      "price": 7.69,
      "volume": 584.0
    },
    {
      "key": "2007-W24",
      "price": 5.86,
      "volume": 44.0
    },
    {
      "key": "2007-W25",
      "price": 19.38,
      "volume": 293.0
    },
    {
      "key": "2007-W26",
      "price": 8.0,
      "volume": 44.0
    },
    {
      "key": "2007-W28",
      "price": 8.1,
      "volume": 18.0
    },
    {
      "key": "2007-W30",
      "price": 5.49,
      "volume": 210.0
    },
    {
      "key": "2007-W31",
      "price": 5.4,
      "volume": 67.0
    },
    {
      "key": "2007-W32",
      "price": 8.0,
      "volume": 34.0
    },
    {
      "key": "2007-W34",
      "price": 8.91,
      "volume": 330.0
    },
    {
      "key": "2007-W35",
      "price": 3.8,
      "volume": 40.0
    },
    {
      "key": "2007-W38",
      "price": 5.81,
      "volume": 198.0
    },
    {
      "key": "2007-W41",
      "price": 5.0,
      "volume": 4.0
    },
    {
      "key": "2007-W45",
      "price": 90.0,
      "volume": 28.0
    },
    {
      "key": "2008-W12",
      "price": 45.0,
      "volume": 90.0
    },
    {
      "key": "2008-W23",
      "price": 5.0,
      "volume": 40.0
    },
    {
      "key": "2008-W25",
      "price": 10.0,
      "volume": 108.0
    },
    {
      "key": "2008-W27",
      "price": 8.55,
      "volume": 258.0
    },
    {
      "key": "2008-W33",
      "price": 19.0,
      "volume": 45.0
    },
    {
      "key": "2008-W34",
      "price": 10.0,
      "volume": 14.0
    },
    {
      "key": "2008-W36",
      "price": 13.8,
      "volume": 31.0
    },
    {
      "key": "2008-W37",
      "price": 7.73,
      "volume": 352.0
    },
    {
      "key": "2008-W40",
      "price": 13.23,
      "volume": 47.0
    },
    {
      "key": "2009-W24",
      "price": 7.0,
      "volume": 13.0
    },
    {
      "key": "2009-W25",
      "price": 8.62,
      "volume": 34.0
    },
    {
      "key": "2009-W27",
      "price": 9.5,
      "volume": 141.0
    },
    {
      "key": "2009-W28",
      "price": 9.13,
      "volume": 90.0
    },
    {
      "key": "2009-W30",
      "price": 7.5,
      "volume": 48.0
    },
    {
      "key": "2009-W31",
      "price": 8.0,
      "volume": 36.0
    },
    {
      "key": "2009-W33",
      "price": 11.5,
      "volume": 80.0
    },
    {
      "key": "2009-W34",
      "price": 9.56,
      "volume": 155.0
    },
    {
      "key": "2009-W37",
      "price": 10.0,
      "volume": 16.0
    },
    {
      "key": "2009-W38",
      "price": 10.0,
      "volume": 17.0
    },
    {
      "key": "2009-W42",
      "price": 13.4,
      "volume": 45.0
    },
    {
      "key": "2010-W22",
      "price": 11.73,
      "volume": 63.0
    },
    {
      "key": "2010-W24",
      "price": 5.29,
      "volume": 37.0
    },
    {
      "key": "2010-W25",
      "price": 5.35,
      "volume": 49.0
    },
    {
      "key": "2010-W27",
      "price": 8.47,
      "volume": 66.0
    },
    {
      "key": "2010-W28",
      "price": 4.0,
      "volume": 15.0
    },
    {
      "key": "2010-W32",
      "price": 16.82,
      "volume": 22.0
    },
    {
      "key": "2010-W35",
      "price": 20.0,
      "volume": 12.0
    },
    {
      "key": "2010-W36",
      "price": 10.0,
      "volume": 17.0
    },
    {
      "key": "2011-W22",
      "price": 19.25,
      "volume": 72.0
    },
    {
      "key": "2011-W23",
      "price": 18.0,
      "volume": 34.0
    },
    {
      "key": "2011-W27",
      "price": 20.46,
      "volume": 169.0
    },
    {
      "key": "2011-W28",
      "price": 11.31,
      "volume": 495.0
    },
    {
      "key": "2011-W29",
      "price": 5.87,
      "volume": 157.0
    },
    {
      "key": "2011-W30",
      "price": 41.34,
      "volume": 84.0
    },
    {
      "key": "2011-W31",
      "price": 17.29,
      "volume": 35.0
    },
    {
      "key": "2011-W34",
      "price": 64.38,
      "volume": 268.0
    },
    {
      "key": "2011-W35",
      "price": 40.0,
      "volume": 15.0
    },
    {
      "key": "2011-W36",
      "price": 30.0,
      "volume": 19.0
    },
    {
      "key": "2011-W37",
      "price": 24.26,
      "volume": 497.0
    },
    {
      "key": "2011-W38",
      "price": 12.77,
      "volume": 103.0
    },
    {
      "key": "2011-W39",
      "price": 15.0,
      "volume": 13.0
    },
    {
      "key": "2011-W40",
      "price": 26.72,
      "volume": 115.0
    },
    {
      "key": "2011-W41",
      "price": 32.5,
      "volume": 191.0
    },
    {
      "key": "2011-W42",
      "price": 20.0,
      "volume": 34.0
    },
    {
      "key": "2012-W20",
      "price": 10.0,
      "volume": 17.0
    },
    {
      "key": "2012-W23",
      "price": 9.12,
      "volume": 104.0
    },
    {
      "key": "2012-W26",
      "price": 9.7,
      "volume": 206.0
    },
    {
      "key": "2012-W27",
      "price": 9.89,
      "volume": 76.0
    },
    {
      "key": "2012-W31",
      "price": 25.0,
      "volume": 9.0
    },
    {
      "key": "2012-W32",
      "price": 15.51,
      "volume": 49.0
    },
    {
      "key": "2012-W34",
      "price": 31.44,
      "volume": 28.0
    },
    {
      "key": "2012-W35",
      "price": 14.44,
      "volume": 90.0
    },
    {
      "key": "2012-W36",
      "price": 10.0,
      "volume": 17.0
    },
    {
      "key": "2013-W20",
      "price": 29.96,
      "volume": 79.0
    },
    {
      "key": "2013-W21",
      "price": 13.17,
      "volume": 92.0
    },
    {
      "key": "2013-W22",
      "price": 24.25,
      "volume": 124.0
    },
    {
      "key": "2013-W23",
      "price": 22.55,
      "volume": 117.0
    },
    {
      "key": "2013-W24",
      "price": 3.0,
      "volume": 20.0
    },
    {
      "key": "2013-W25",
      "price": 28.36,
      "volume": 275.0
    },
    {
      "key": "2013-W26",
      "price": 14.25,
      "volume": 404.0
    },
    {
      "key": "2013-W27",
      "price": 5.0,
      "volume": 4.0
    },
    {
      "key": "2013-W28",
      "price": 18.21,
      "volume": 212.0
    },
    {
      "key": "2013-W29",
      "price": 48.0,
      "volume": 20.0
    },
    {
      "key": "2013-W30",
      "price": 43.77,
      "volume": 165.0
    },
    {
      "key": "2013-W31",
      "price": 24.52,
      "volume": 301.0
    },
    {
      "key": "2013-W32",
      "price": 27.22,
      "volume": 61.0
    },
    {
      "key": "2013-W33",
      "price": 16.41,
      "volume": 353.0
    },
    {
      "key": "2013-W34",
      "price": 8.59,
      "volume": 358.0
    },
    {
      "key": "2013-W35",
      "price": 40.39,
      "volume": 149.0
    },
    {
      "key": "2013-W36",
      "price": 22.87,
      "volume": 316.0
    },
    {
      "key": "2013-W37",
      "price": 53.52,
      "volume": 54.0
    },
    {
      "key": "2013-W39",
      "price": 38.0,
      "volume": 18.0
    },
    {
      "key": "2013-W40",
      "price": 60.0,
      "volume": 43.0
    },
    {
      "key": "2013-W41",
      "price": 58.02,
      "volume": 155.0
    },
    {
      "key": "2014-W20",
      "price": 21.84,
      "volume": 19.0
    },
    {
      "key": "2014-W21",
      "price": 17.72,
      "volume": 197.0
    },
    {
      "key": "2014-W22",
      "price": 30.0,
      "volume": 22.0
    },
    {
      "key": "2014-W23",
      "price": 17.14,
      "volume": 155.0
    },
    {
      "key": "2014-W24",
      "price": 35.0,
      "volume": 8.0
    },
    {
      "key": "2014-W25",
      "price": 12.32,
      "volume": 278.0
    },
    {
      "key": "2014-W26",
      "price": 6.99,
      "volume": 145.0
    },
    {
      "key": "2014-W27",
      "price": 8.0,
      "volume": 197.0
    },
    {
      "key": "2014-W28",
      "price": 32.96,
      "volume": 140.0
    },
    {
      "key": "2014-W30",
      "price": 50.0,
      "volume": 14.0
    },
    {
      "key": "2014-W31",
      "price": 124.75,
      "volume": 57.0
    },
    {
      "key": "2014-W32",
      "price": 10.69,
      "volume": 1041.0
    },
    {
      "key": "2014-W33",
      "price": 8.5,
      "volume": 10.0
    },
    {
      "key": "2014-W34",
      "price": 26.52,
      "volume": 64.0
    },
    {
      "key": "2014-W35",
      "price": 17.53,
      "volume": 196.0
    },
    {
      "key": "2014-W36",
      "price": 11.8,
      "volume": 50.0
    },
    {
      "key": "2014-W38",
      "price": 5.0,
      "volume": 8.0
    },
    {
      "key": "2014-W39",
      "price": 50.0,
      "volume": 17.0
    },
    {
      "key": "2014-W40",
      "price": 90.0,
      "volume": 16.0
    },
    {
      "key": "2014-W41",
      "price": 18.08,
      "volume": 154.0
    },
    {
      "key": "2015-W18",
      "price": 28.33,
      "volume": 27.0
    },
    {
      "key": "2015-W19",
      "price": 13.5,
      "volume": 40.0
    },
    {
      "key": "2015-W20",
      "price": 10.0,
      "volume": 27.0
    },
    {
      "key": "2015-W21",
      "price": 45.0,
      "volume": 15.0
    },
    {
      "key": "2015-W22",
      "price": 25.03,
      "volume": 154.0
    },
    {
      "key": "2015-W24",
      "price": 12.91,
      "volume": 309.0
    },
    {
      "key": "2015-W26",
      "price": 25.0,
      "volume": 7.0
    },
    {
      "key": "2015-W28",
      "price": 16.0,
      "volume": 319.0
    },
    {
      "key": "2015-W30",
      "price": 17.73,
      "volume": 141.0
    },
    {
      "key": "2015-W31",
      "price": 8.0,
      "volume": 32.0
    },
    {
      "key": "2015-W32",
      "price": 11.0,
      "volume": 154.0
    },
    {
      "key": "2015-W35",
      "price": 12.0,
      "volume": 18.0
    },
    {
      "key": "2015-W36",
      "price": 20.0,
      "volume": 46.0
    },
    {
      "key": "2015-W37",
      "price": 20.0,
      "volume": 12.0
    },
    {
      "key": "2015-W38",
      "price": 10.55,
      "volume": 475.0
    },
    {
      "key": "2015-W41",
      "price": 14.0,
      "volume": 21.0
    },
    {
      "key": "2015-W42",
      "price": 82.03,
      "volume": 231.0
    },
    {
      "key": "2015-W46",
      "price": 60.0,
      "volume": 540.0
    },
    {
      "key": "2015-W47",
      "price": 0.0,
      "volume": 4.0
    },
    {
      "key": "2016-W08",
      "price": 80.0,
      "volume": 36.0
    },
    {
      "key": "2016-W18",
      "price": 14.44,
      "volume": 36.0
    },
    {
      "key": "2016-W20",
      "price": 18.76,
      "volume": 112.0
    },
    {
      "key": "2016-W21",
      "price": 27.22,
      "volume": 122.0
    },
    {
      "key": "2016-W22",
      "price": 16.3,
      "volume": 436.0
    },
    {
      "key": "2016-W23",
      "price": 7.05,
      "volume": 21.0
    },
    {
      "key": "2016-W24",
      "price": 16.69,
      "volume": 67.0
    },
    {
      "key": "2016-W25",
      "price": 25.34,
      "volume": 215.0
    },
    {
      "key": "2016-W26",
      "price": 23.0,
      "volume": 2.0
    },
    {
      "key": "2016-W28",
      "price": 18.31,
      "volume": 906.0
    },
    {
      "key": "2016-W29",
      "price": 13.85,
      "volume": 469.0
    },
    {
      "key": "2016-W30",
      "price": 10.84,
      "volume": 512.0
    },
    {
      "key": "2016-W32",
      "price": 19.77,
      "volume": 133.0
    },
    {
      "key": "2016-W33",
      "price": 14.95,
      "volume": 203.0
    },
    {
      "key": "2016-W34",
      "price": 20.92,
      "volume": 55.0
    },
    {
      "key": "2016-W35",
      "price": 17.34,
      "volume": 78.0
    },
    {
      "key": "2016-W36",
      "price": 49.67,
      "volume": 21.0
    },
    {
      "key": "2016-W37",
      "price": 24.12,
      "volume": 139.0
    },
    {
      "key": "2016-W38",
      "price": 61.28,
      "volume": 402.0
    },
    {
      "key": "2016-W42",
      "price": 69.68,
      "volume": 14.0
    },
    {
      "key": "2016-W43",
      "price": 17.07,
      "volume": 47.0
    },
    {
      "key": "2016-W46",
      "price": 40.0,
      "volume": 53.0
    },
    {
      "key": "2016-W47",
      "price": 16.15,
      "volume": 172.0
    },
    {
      "key": "2016-W52",
      "price": 10.0,
      "volume": 84.0
    },
    {
      "key": "2017-W17",
      "price": 24.69,
      "volume": 115.0
    },
    {
      "key": "2017-W18",
      "price": 16.48,
      "volume": 200.0
    },
    {
      "key": "2017-W19",
      "price": 17.78,
      "volume": 539.0
    },
    {
      "key": "2017-W22",
      "price": 15.14,
      "volume": 829.0
    },
    {
      "key": "2017-W23",
      "price": 7.39,
      "volume": 727.0
    },
    {
      "key": "2017-W24",
      "price": 13.92,
      "volume": 212.0
    },
    {
      "key": "2017-W25",
      "price": 8.06,
      "volume": 105.0
    },
    {
      "key": "2017-W26",
      "price": 9.95,
      "volume": 487.0
    },
    {
      "key": "2017-W27",
      "price": 9.26,
      "volume": 75.0
    },
    {
      "key": "2017-W28",
      "price": 18.45,
      "volume": 88.0
    },
    {
      "key": "2017-W29",
      "price": 16.25,
      "volume": 343.0
    },
    {
      "key": "2017-W30",
      "price": 8.1,
      "volume": 87.0
    },
    {
      "key": "2017-W31",
      "price": 15.07,
      "volume": 58.0
    },
    {
      "key": "2017-W32",
      "price": 16.03,
      "volume": 504.0
    },
    {
      "key": "2017-W33",
      "price": 14.77,
      "volume": 108.0
    },
    {
      "key": "2017-W34",
      "price": 16.1,
      "volume": 23.0
    },
    {
      "key": "2017-W35",
      "price": 61.22,
      "volume": 79.0
    },
    {
      "key": "2017-W36",
      "price": 34.29,
      "volume": 298.0
    },
    {
      "key": "2017-W37",
      "price": 8.65,
      "volume": 213.0
    },
    {
      "key": "2017-W41",
      "price": 13.13,
      "volume": 179.0
    },
    {
      "key": "2017-W43",
      "price": 25.0,
      "volume": 24.0
    },
    {
      "key": "2017-W44",
      "price": 14.08,
      "volume": 310.0
    },
    {
      "key": "2017-W48",
      "price": 10.61,
      "volume": 460.0
    },
    {
      "key": "2017-W52",
      "price": 90.0,
      "volume": 20.0
    },
    {
      "key": "2018-W18",
      "price": 11.25,
      "volume": 284.0
    },
    {
      "key": "2018-W19",
      "price": 15.0,
      "volume": 10.0
    },
    {
      "key": "2018-W21",
      "price": 10.37,
      "volume": 372.0
    },
    {
      "key": "2018-W24",
      "price": 14.53,
      "volume": 15.0
    },
    {
      "key": "2018-W26",
      "price": 24.5,
      "volume": 36.0
    },
    {
      "key": "2018-W27",
      "price": 25.23,
      "volume": 69.0
    },
    {
      "key": "2018-W28",
      "price": 11.44,
      "volume": 430.0
    },
    {
      "key": "2018-W29",
      "price": 20.61,
      "volume": 121.0
    },
    {
      "key": "2018-W30",
      "price": 25.0,
      "volume": 7.0
    },
    {
      "key": "2018-W31",
      "price": 15.5,
      "volume": 687.0
    },
    {
      "key": "2018-W32",
      "price": 16.23,
      "volume": 196.0
    },
    {
      "key": "2018-W33",
      "price": 7.91,
      "volume": 752.0
    },
    {
      "key": "2018-W34",
      "price": 11.56,
      "volume": 147.0
    },
    {
      "key": "2018-W35",
      "price": 10.65,
      "volume": 1262.0
    },
    {
      "key": "2018-W36",
      "price": 14.96,
      "volume": 198.0
    },
    {
      "key": "2018-W38",
      "price": 9.92,
      "volume": 362.0
    },
    {
      "key": "2018-W39",
      "price": 39.2,
      "volume": 81.0
    },
    {
      "key": "2018-W40",
      "price": 11.58,
      "volume": 50.0
    },
    {
      "key": "2018-W41",
      "price": 26.01,
      "volume": 44.0
    },
    {
      "key": "2018-W42",
      "price": 29.68,
      "volume": 94.0
    },
    {
      "key": "2019-W06",
      "price": 13.41,
      "volume": 41.0
    },
    {
      "key": "2019-W17",
      "price": 38.87,
      "volume": 39.0
    },
    {
      "key": "2019-W18",
      "price": 21.05,
      "volume": 271.0
    },
    {
      "key": "2019-W19",
      "price": 13.66,
      "volume": 225.0
    },
    {
      "key": "2019-W20",
      "price": 11.48,
      "volume": 504.0
    },
    {
      "key": "2019-W21",
      "price": 6.69,
      "volume": 1304.0
    },
    {
      "key": "2019-W22",
      "price": 9.76,
      "volume": 41.0
    },
    {
      "key": "2019-W23",
      "price": 6.12,
      "volume": 652.0
    },
    {
      "key": "2019-W24",
      "price": 7.02,
      "volume": 101.0
    },
    {
      "key": "2019-W26",
      "price": 9.7,
      "volume": 353.0
    },
    {
      "key": "2019-W27",
      "price": 10.0,
      "volume": 15.0
    },
    {
      "key": "2019-W28",
      "price": 7.49,
      "volume": 191.0
    },
    {
      "key": "2019-W29",
      "price": 11.12,
      "volume": 800.0
    },
    {
      "key": "2019-W30",
      "price": 7.36,
      "volume": 22.0
    },
    {
      "key": "2019-W31",
      "price": 15.92,
      "volume": 370.0
    },
    {
      "key": "2019-W32",
      "price": 6.26,
      "volume": 190.0
    },
    {
      "key": "2019-W34",
      "price": 24.49,
      "volume": 217.0
    },
    {
      "key": "2019-W35",
      "price": 11.69,
      "volume": 81.0
    },
    {
      "key": "2019-W36",
      "price": 21.7,
      "volume": 70.0
    },
    {
      "key": "2019-W37",
      "price": 13.29,
      "volume": 48.0
    },
    {
      "key": "2019-W38",
      "price": 13.44,
      "volume": 361.0
    },
    {
      "key": "2019-W40",
      "price": 14.39,
      "volume": 438.0
    },
    {
      "key": "2019-W41",
      "price": 5.66,
      "volume": 179.0
    },
    {
      "key": "2019-W42",
      "price": 5.0,
      "volume": 2.0
    },
    {
      "key": "2019-W49",
      "price": 60.0,
      "volume": 90.0
    },
    {
      "key": "2020-W17",
      "price": 15.0,
      "volume": 14.0
    },
    {
      "key": "2020-W19",
      "price": 7.98,
      "volume": 457.0
    },
    {
      "key": "2020-W20",
      "price": 10.13,
      "volume": 171.0
    },
    {
      "key": "2020-W22",
      "price": 17.22,
      "volume": 100.0
    },
    {
      "key": "2020-W23",
      "price": 12.88,
      "volume": 320.0
    },
    {
      "key": "2020-W24",
      "price": 7.36,
      "volume": 75.0
    },
    {
      "key": "2020-W25",
      "price": 15.31,
      "volume": 74.0
    },
    {
      "key": "2020-W26",
      "price": 7.82,
      "volume": 626.0
    },
    {
      "key": "2020-W28",
      "price": 20.58,
      "volume": 170.0
    },
    {
      "key": "2020-W29",
      "price": 8.28,
      "volume": 503.0
    },
    {
      "key": "2020-W30",
      "price": 5.0,
      "volume": 40.0
    },
    {
      "key": "2020-W31",
      "price": 11.64,
      "volume": 122.0
    },
    {
      "key": "2020-W32",
      "price": 31.0,
      "volume": 20.0
    },
    {
      "key": "2020-W33",
      "price": 15.34,
      "volume": 249.0
    },
    {
      "key": "2020-W34",
      "price": 14.0,
      "volume": 437.0
    },
    {
      "key": "2020-W35",
      "price": 12.82,
      "volume": 179.0
    },
    {
      "key": "2020-W36",
      "price": 2.0,
      "volume": 40.0
    },
    {
      "key": "2020-W37",
      "price": 9.73,
      "volume": 894.0
    },
    {
      "key": "2020-W38",
      "price": 7.0,
      "volume": 16.0
    },
    {
      "key": "2020-W39",
      "price": 22.0,
      "volume": 6.0
    },
    {
      "key": "2020-W41",
      "price": 23.22,
      "volume": 49.0
    },
    {
      "key": "2020-W42",
      "price": 10.69,
      "volume": 117.0
    },
    {
      "key": "2021-W09",
      "price": 90.0,
      "volume": 25.0
    },
    {
      "key": "2021-W14",
      "price": 34.21,
      "volume": 148.0
    },
    {
      "key": "2021-W16",
      "price": 25.0,
      "volume": 38.0
    },
    {
      "key": "2021-W19",
      "price": 11.34,
      "volume": 597.0
    },
    {
      "key": "2021-W23",
      "price": 6.54,
      "volume": 265.0
    },
    {
      "key": "2021-W24",
      "price": 4.55,
      "volume": 338.0
    },
    {
      "key": "2021-W25",
      "price": 4.8,
      "volume": 65.0
    },
    {
      "key": "2021-W26",
      "price": 5.5,
      "volume": 30.0
    },
    {
      "key": "2021-W27",
      "price": 5.71,
      "volume": 290.0
    },
    {
      "key": "2021-W30",
      "price": 7.07,
      "volume": 111.0
    },
    {
      "key": "2021-W32",
      "price": 30.92,
      "volume": 130.0
    },
    {
      "key": "2021-W33",
      "price": 20.76,
      "volume": 104.0
    },
    {
      "key": "2021-W35",
      "price": 13.92,
      "volume": 113.0
    },
    {
      "key": "2021-W36",
      "price": 10.5,
      "volume": 133.0
    },
    {
      "key": "2021-W38",
      "price": 12.46,
      "volume": 198.0
    },
    {
      "key": "2021-W39",
      "price": 11.64,
      "volume": 58.0
    },
    {
      "key": "2021-W41",
      "price": 180.0,
      "volume": 16.0
    },
    {
      "key": "2021-W43",
      "price": 16.29,
      "volume": 70.0
    },
    {
      "key": "2021-W44",
      "price": 13.5,
      "volume": 16.0
    },
    {
      "key": "2022-W18",
      "price": 30.0,
      "volume": 6.0
    },
    {
      "key": "2022-W19",
      "price": 20.0,
      "volume": 31.0
    },
    {
      "key": "2022-W20",
      "price": 18.92,
      "volume": 79.0
    },
    {
      "key": "2022-W21",
      "price": 10.0,
      "volume": 22.0
    },
    {
      "key": "2022-W22",
      "price": 17.33,
      "volume": 99.0
    },
    {
      "key": "2022-W23",
      "price": 15.0,
      "volume": 3.0
    },
    {
      "key": "2022-W25",
      "price": 17.21,
      "volume": 503.0
    },
    {
      "key": "2022-W27",
      "price": 19.69,
      "volume": 180.0
    },
    {
      "key": "2022-W28",
      "price": 10.85,
      "volume": 56.0
    },
    {
      "key": "2022-W30",
      "price": 12.21,
      "volume": 347.0
    },
    {
      "key": "2022-W31",
      "price": 12.27,
      "volume": 52.0
    },
    {
      "key": "2022-W32",
      "price": 25.29,
      "volume": 40.0
    },
    {
      "key": "2022-W33",
      "price": 11.02,
      "volume": 811.0
    },
    {
      "key": "2022-W34",
      "price": 24.0,
      "volume": 20.0
    },
    {
      "key": "2022-W36",
      "price": 34.8,
      "volume": 128.0
    },
    {
      "key": "2022-W37",
      "price": 19.55,
      "volume": 101.0
    },
    {
      "key": "2022-W38",
      "price": 35.0,
      "volume": 11.0
    },
    {
      "key": "2022-W39",
      "price": 38.21,
      "volume": 25.0
    },
    {
      "key": "2022-W40",
      "price": 21.97,
      "volume": 159.0
    },
    {
      "key": "2022-W42",
      "price": 52.0,
      "volume": 14.0
    },
    {
      "key": "2022-W43",
      "price": 29.96,
      "volume": 57.0
    },
    {
      "key": "2022-W44",
      "price": 10.0,
      "volume": 14.0
    },
    {
      "key": "2022-W47",
      "price": 22.5,
      "volume": 12.0
    },
    {
      "key": "2023-W16",
      "price": 10.75,
      "volume": 32.0
    },
    {
      "key": "2023-W17",
      "price": 8.0,
      "volume": 28.0
    },
    {
      "key": "2023-W18",
      "price": 32.82,
      "volume": 338.0
    },
    {
      "key": "2023-W19",
      "price": 26.9,
      "volume": 50.0
    },
    {
      "key": "2023-W21",
      "price": 12.09,
      "volume": 797.0
    },
    {
      "key": "2023-W22",
      "price": 22.83,
      "volume": 183.0
    },
    {
      "key": "2023-W23",
      "price": 28.2,
      "volume": 97.0
    },
    {
      "key": "2023-W24",
      "price": 9.52,
      "volume": 44.0
    },
    {
      "key": "2023-W25",
      "price": 10.42,
      "volume": 152.0
    },
    {
      "key": "2023-W26",
      "price": 40.0,
      "volume": 20.0
    },
    {
      "key": "2023-W28",
      "price": 13.63,
      "volume": 140.0
    },
    {
      "key": "2023-W29",
      "price": 60.0,
      "volume": 16.0
    },
    {
      "key": "2023-W30",
      "price": 19.2,
      "volume": 30.0
    },
    {
      "key": "2023-W31",
      "price": 11.67,
      "volume": 39.0
    },
    {
      "key": "2023-W32",
      "price": 20.37,
      "volume": 87.0
    },
    {
      "key": "2023-W34",
      "price": 27.94,
      "volume": 87.0
    },
    {
      "key": "2023-W35",
      "price": 17.17,
      "volume": 30.0
    },
    {
      "key": "2023-W36",
      "price": 34.19,
      "volume": 28.0
    },
    {
      "key": "2023-W37",
      "price": 13.95,
      "volume": 822.0
    },
    {
      "key": "2023-W38",
      "price": 8.27,
      "volume": 252.0
    },
    {
      "key": "2023-W41",
      "price": 25.0,
      "volume": 16.0
    },
    {
      "key": "2023-W42",
      "price": 13.78,
      "volume": 66.0
    },
    {
      "key": "2024-W18",
      "price": 4.6,
      "volume": 202.0
    },
    {
      "key": "2024-W19",
      "price": 13.06,
      "volume": 520.0
    },
    {
      "key": "2024-W20",
      "price": 10.0,
      "volume": 21.0
    },
    {
      "key": "2024-W23",
      "price": 28.3,
      "volume": 51.0
    },
    {
      "key": "2024-W25",
      "price": 9.6,
      "volume": 34.0
    },
    {
      "key": "2024-W27",
      "price": 10.0,
      "volume": 13.0
    },
    {
      "key": "2024-W32",
      "price": 17.84,
      "volume": 141.0
    },
    {
      "key": "2024-W33",
      "price": 7.38,
      "volume": 128.0
    },
    {
      "key": "2024-W34",
      "price": 15.32,
      "volume": 191.0
    },
    {
      "key": "2024-W35",
      "price": 9.48,
      "volume": 195.0
    },
    {
      "key": "2024-W38",
      "price": 5.0,
      "volume": 9.0
    },
    {
      "key": "2024-W39",
      "price": 15.0,
      "volume": 10.0
    },
    {
      "key": "2024-W40",
      "price": 12.5,
      "volume": 36.0
    },
    {
      "key": "2024-W49",
      "price": 27.7,
      "volume": 150.0
    },
    {
      "key": "2025-W22",
      "price": 32.27,
      "volume": 45.0
    },
    {
      "key": "2025-W26",
      "price": 60.0,
      "volume": 9.0
    },
    {
      "key": "2025-W27",
      "price": 36.79,
      "volume": 56.0
    },
    {
      "key": "2025-W28",
      "price": 60.0,
      "volume": 19.0
    },
    {
      "key": "2025-W29",
      "price": 22.62,
      "volume": 82.0
    },
    {
      "key": "2025-W30",
      "price": 12.73,
      "volume": 424.0
    },
    {
      "key": "2025-W32",
      "price": 24.39,
      "volume": 217.0
    },
    {
      "key": "2025-W33",
      "price": 17.02,
      "volume": 249.0
    },
    {
      "key": "2025-W35",
      "price": 26.92,
      "volume": 39.0
    },
    {
      "key": "2025-W36",
      "price": 18.33,
      "volume": 51.0
    },
    {
      "key": "2025-W38",
      "price": 21.85,
      "volume": 161.0
    },
    {
      "key": "2025-W40",
      "price": 60.0,
      "volume": 4.0
    }
  ],
  "monthly": [
    {
      "key": "2017-12",
      "price": 13.92,
      "volume": 480.0
    },
    {
      "key": "2018-05",
      "price": 10.82,
      "volume": 666.0
    },
    {
      "key": "2018-06",
      "price": 21.57,
      "volume": 51.0
    },
    {
      "key": "2018-07",
      "price": 14.87,
      "volume": 627.0
    },
    {
      "key": "2018-08",
      "price": 11.34,
      "volume": 2928.0
    },
    {
      "key": "2018-09",
      "price": 15.12,
      "volume": 757.0
    },
    {
      "key": "2018-10",
      "price": 24.01,
      "volume": 188.0
    },
    {
      "key": "2019-02",
      "price": 13.41,
      "volume": 41.0
    },
    {
      "key": "2019-04",
      "price": 27.43,
      "volume": 181.0
    },
    {
      "key": "2019-05",
      "price": 9.18,
      "volume": 2173.0
    },
    {
      "key": "2019-06",
      "price": 7.41,
      "volume": 1136.0
    },
    {
      "key": "2019-07",
      "price": 10.34,
      "volume": 1038.0
    },
    {
      "key": "2019-08",
      "price": 15.7,
      "volume": 835.0
    },
    {
      "key": "2019-09",
      "price": 14.51,
      "volume": 492.0
    },
    {
      "key": "2019-10",
      "price": 11.84,
      "volume": 619.0
    },
    {
      "key": "2019-12",
      "price": 60.0,
      "volume": 90.0
    },
    {
      "key": "2020-04",
      "price": 15.0,
      "volume": 14.0
    },
    {
      "key": "2020-05",
      "price": 9.76,
      "volume": 728.0
    },
    {
      "key": "2020-06",
      "price": 9.77,
      "volume": 1095.0
    },
    {
      "key": "2020-07",
      "price": 11.15,
      "volume": 809.0
    },
    {
      "key": "2020-08",
      "price": 14.39,
      "volume": 911.0
    },
    {
      "key": "2020-09",
      "price": 9.44,
      "volume": 956.0
    },
    {
      "key": "2020-10",
      "price": 14.39,
      "volume": 166.0
    },
    {
      "key": "2021-03",
      "price": 90.0,
      "volume": 25.0
    },
    {
      "key": "2021-04",
      "price": 32.33,
      "volume": 186.0
    },
    {
      "key": "2021-05",
      "price": 11.34,
      "volume": 597.0
    },
    {
      "key": "2021-06",
      "price": 5.36,
      "volume": 668.0
    },
    {
      "key": "2021-07",
      "price": 6.04,
      "volume": 431.0
    },
    {
      "key": "2021-08",
      "price": 26.4,
      "volume": 234.0
    },
    {
      "key": "2021-09",
      "price": 12.18,
      "volume": 502.0
    },
    {
      "key": "2021-10",
      "price": 46.75,
      "volume": 86.0
    },
    {
      "key": "2021-11",
      "price": 13.5,
      "volume": 16.0
    },
    {
      "key": "2022-05",
      "price": 18.57,
      "volume": 171.0
    },
    {
      "key": "2022-06",
      "price": 17.05,
      "volume": 572.0
    },
    {
      "key": "2022-07",
      "price": 14.39,
      "volume": 583.0
    },
    {
      "key": "2022-08",
      "price": 11.99,
      "volume": 923.0
    },
    {
      "key": "2022-09",
      "price": 28.33,
      "volume": 245.0
    },
    {
      "key": "2022-10",
      "price": 27.04,
      "volume": 250.0
    },
    {
      "key": "2022-11",
      "price": 15.77,
      "volume": 26.0
    },
    {
      "key": "2023-04",
      "price": 9.47,
      "volume": 60.0
    },
    {
      "key": "2023-05",
      "price": 19.39,
      "volume": 1332.0
    },
    {
      "key": "2023-06",
      "price": 17.08,
      "volume": 349.0
    },
    {
      "key": "2023-07",
      "price": 18.52,
      "volume": 186.0
    },
    {
      "key": "2023-08",
      "price": 21.0,
      "volume": 238.0
    },
    {
      "key": "2023-09",
      "price": 13.27,
      "volume": 1107.0
    },
    {
      "key": "2023-10",
      "price": 15.97,
      "volume": 82.0
    },
    {
      "key": "2024-04",
      "price": 4.6,
      "volume": 202.0
    },
    {
      "key": "2024-05",
      "price": 12.94,
      "volume": 541.0
    },
    {
      "key": "2024-06",
      "price": 20.82,
      "volume": 85.0
    },
    {
      "key": "2024-07",
      "price": 10.0,
      "volume": 13.0
    },
    {
      "key": "2024-08",
      "price": 12.69,
      "volume": 632.0
    },
    {
      "key": "2024-09",
      "price": 9.71,
      "volume": 42.0
    },
    {
      "key": "2024-10",
      "price": 12.5,
      "volume": 36.0
    },
    {
      "key": "2024-12",
      "price": 27.7,
      "volume": 150.0
    },
    {
      "key": "2025-05",
      "price": 32.27,
      "volume": 45.0
    },
    {
      "key": "2025-06",
      "price": 60.0,
      "volume": 9.0
    },
    {
      "key": "2025-07",
      "price": 17.99,
      "volume": 581.0
    },
    {
      "key": "2025-08",
      "price": 20.95,
      "volume": 505.0
    },
    {
      "key": "2025-09",
      "price": 21.01,
      "volume": 212.0
    },
    {
      "key": "2025-10",
      "price": 60.0,
      "volume": 4.0
    }
  ],
  "yearly": [
    {
      "key": "2006",
      "price": 12.2,
      "volume": 1719.0
    },
    {
      "key": "2007",
      "price": 10.2,
      "volume": 1940.0
    },
    {
      "key": "2008",
      "price": 12.49,
      "volume": 985.0
    },
    {
      "key": "2009",
      "price": 9.67,
      "volume": 675.0
    },
    {
      "key": "2010",
      "price": 9.24,
      "volume": 281.0
    },
    {
      "key": "2011",
      "price": 25.21,
      "volume": 2301.0
    },
    {
      "key": "2012",
      "price": 12.09,
      "volume": 596.0
    },
    {
      "key": "2013",
      "price": 24.46,
      "volume": 3320.0
    },
    {
      "key": "2014",
      "price": 17.22,
      "volume": 2788.0
    },
    {
      "key": "2015",
      "price": 30.27,
      "volume": 2572.0
    },
    {
      "key": "2016",
      "price": 22.15,
      "volume": 4335.0
    },
    {
      "key": "2017",
      "price": 15.24,
      "volume": 6083.0
    },
    {
      "key": "2018",
      "price": 12.8,
      "volume": 5217.0
    },
    {
      "key": "2019",
      "price": 11.75,
      "volume": 6605.0
    },
    {
      "key": "2020",
      "price": 11.02,
      "volume": 4679.0
    },
    {
      "key": "2021",
      "price": 13.75,
      "volume": 2745.0
    },
    {
      "key": "2022",
      "price": 16.79,
      "volume": 2770.0
    },
    {
      "key": "2023",
      "price": 16.93,
      "volume": 3354.0
    },
    {
      "key": "2024",
      "price": 13.44,
      "volume": 1701.0
    },
    {
      "key": "2025",
      "price": 20.44,
      "volume": 1356.0
    }
  ],
  "market_compare": {
    "month": "2025-10",
    "markets_volume": [
      {
        "market": "台北一",
        "price": 60.0,
        "volume": 4.0
      }
    ],
    "markets_price": [
      {
        "market": "台北一",
        "price": 60.0,
        "volume": 4.0
      }
    ]
  }
}